os_http/__init__.py
os_http/shell.py
os_http/version.py
os_http/tests/__init__.py
os_http/tests/base.py
os_http/tests/test_os_http.py
os_http-0.1.0.dist-info/DESCRIPTION.rst
os_http-0.1.0.dist-info/METADATA
os_http-0.1.0.dist-info/RECORD
os_http-0.1.0.dist-info/WHEEL
os_http-0.1.0.dist-info/entry_points.txt
os_http-0.1.0.dist-info/metadata.json
os_http-0.1.0.dist-info/pbr.json
os_http-0.1.0.dist-info/top_level.txt
