Metadata-Version: 2.0
Name: os-http
Version: 0.1.0
Summary: Simple HTTP CLI for OpenStack
Home-page: http://www.openstack.org/
Author: OpenStack
Author-email: openstack-dev@lists.openstack.org
License: UNKNOWN
Platform: UNKNOWN
Classifier: Environment :: OpenStack
Classifier: Intended Audience :: Information Technology
Classifier: Intended Audience :: System Administrators
Classifier: License :: OSI Approved :: Apache Software License
Classifier: Operating System :: POSIX :: Linux
Classifier: Programming Language :: Python
Classifier: Programming Language :: Python :: 2
Classifier: Programming Language :: Python :: 2.7
Classifier: Programming Language :: Python :: 3
Classifier: Programming Language :: Python :: 3.3
Classifier: Programming Language :: Python :: 3.4
Requires-Dist: Babel (>=1.3)
Requires-Dist: keystoneauth1
Requires-Dist: os-client-config
Requires-Dist: pbr (>=1.4,<2.0)
Requires-Dist: pygments
